teddy_portal_gun/__init__.py
teddy_portal_gun/__main__.py
teddy_portal_gun/main.py
teddy_portal_gun-0.2.0.dist-info/entry_points.txt
teddy_portal_gun-0.2.0.dist-info/WHEEL
teddy_portal_gun-0.2.0.dist-info/METADATA
teddy_portal_gun-0.2.0.dist-info/RECORD
