Metadata-Version: 2.1
Name: teddy-portal-gun
Version: 0.2.0
Summary: 
Author: Teddy Xinyuan Chen
Author-email: 45612704+tddschn@users.noreply.github.com
Requires-Python: >=3.10,<4.0
Classifier: Programming Language :: Python :: 3
Classifier: Programming Language :: Python :: 3.10
Requires-Dist: typer[all] (<0.4.0)
